{
    "Raise wa Tanin ga Ii": {
        "anime_url": "https://witanime.you/anime/raise-wa-tanin-ga-ii/",
        "type": "TV",
        "mal_id": "56964",
        "1": {
            "streaming_links": [
                "https://yonaplay.net/embed.php?id=16309",
                "https://ok.ru/videoembed/7742854269638",
                "https://videa.hu/player?v=ss5i67A66yLgLB0K",
                "https://www.dailymotion.com/embed/video/x96xcbw",
                "https://ok.ru/videoembed/7742864952006",
                "https://ok.ru/videoembed/7742872160966",
                "https://videa.hu/player?v=SsaqZi6pzuFq3W4j",
                "https://www.dailymotion.com/embed/video/x96xcbw"
            ],
            "downloading_links": [
                "https://www.mediafire.com/file/6sknlhp67445l7d/%5BWitanime.com%5D+RWTGI+EP+01+SD.zip/file",
                "https://workupload.com/file/RAwS6f5p5eD",
                "https://www.mp4upload.com/k4mvf91llcjh",
                "https://gofile.io/d/qgKfeU",
                "https://www.mediafire.com/file/muydb9a4qyw7qdi/%5BWitanime.com%5D+RWTGI+EP+01+HD.zip/file",
                "https://workupload.com/file/ubrrtrAvnZT",
                "https://www.mp4upload.com/iowshg39x8bv",
                "https://gofile.io/d/OstAl8",
                "https://www.mediafire.com/file/fi616fy146snk1o/%5BWitanime.com%5D+RWTGI+EP+01+FHD.zip/file"
            ]
        },
        "2": {
            "streaming_links": [
                "https://yonaplay.net/embed.php?id=16384",
                "https://ok.ru/videoembed/7800184572614",
                "https://videa.hu/player?v=dnIaDgRDTuKALiLW",
                "https://www.dailymotion.com/embed/video/x97bf7i",
                "https://ok.ru/videoembed/7800191257286",
                "https://ok.ru/videoembed/7800195123910",
                "https://videa.hu/player?v=CmGkeRjdgoogaGBD",
                "https://www.dailymotion.com/embed/video/x97bf7i"
            ],
            "downloading_links": [
                "https://www.mediafire.com/file/jtk0y4oil1sufby/%5BWitanime.com%5D+RWTGI+EP+02+SD.zip/file",
                "https://workupload.com/file/GvAe9GfaPTD",
                "https://www.mp4upload.com/fwceo28hcw5g",
                "https://gofile.io/d/IETDVb",
                "https://www.mediafire.com/file/ydw9dik6irah5xf/%5BWitanime.com%5D+RWTGI+EP+02+HD.zip/file",
                "https://workupload.com/file/Lsmhmm5khCt",
                "https://www.mp4upload.com/p4vzl0oaw166",
                "https://gofile.io/d/XPoecg",
                "https://www.mediafire.com/file/02n8s2qxbrf51k8/[Witanime.com]+RWTGI+EP+02+FHD.zip/file"
            ]
        },
        "3": {
            "streaming_links": [
                "https://yonaplay.net/embed.php?id=16451",
                "https://ok.ru/videoembed/7824400845510",
                "https://videa.hu/player?v=pnqcmTrItwBaFT7U",
                "https://www.dailymotion.com/embed/video/x97s0cc",
                "https://ok.ru/videoembed/7824405957318",
                "https://ok.ru/videoembed/7824410675910",
                "https://videa.hu/player?v=bsq9ZuLKUa2v66AX",
                "https://www.dailymotion.com/embed/video/x97s0cc"
            ],
            "downloading_links": [
                "https://www.mediafire.com/file/qter22orp06vhdc/%5BWitanime.com%5D+RWTGI+EP+03+SD.zip/file",
                "https://workupload.com/file/pVtPkN7qAqR",
                "https://www.mp4upload.com/sv9ohnc43y7u",
                "https://gofile.io/d/xLUvAv",
                "https://www.mediafire.com/file/iwnn8egu1vwed3g/%5BWitanime.com%5D+RWTGI+EP+03+HD.zip/file",
                "https://workupload.com/file/QsfeG56VzBr",
                "https://www.mp4upload.com/unf769xhq19d",
                "https://gofile.io/d/sUBh5A",
                "https://www.mediafire.com/file/4i0s5a5w9kbslrr/[Witanime.com]+RWTGI+EP+03+FHD.zip/file"
            ]
        },
        "4": {
            "streaming_links": [
                "https://yonaplay.net/embed.php?id=16510",
                "https://ok.ru/videoembed/7895860185798",
                "https://videa.hu/player?v=AwkyKPKBcmXsvsNB",
                "https://www.dailymotion.com/embed/video/x986fts",
                "https://ok.ru/videoembed/7895867525830",
                "https://ok.ru/videoembed/7895876897478",
                "https://videa.hu/player?v=U7Q8ZvijsIk9kh63",
                "https://www.dailymotion.com/embed/video/x986fts"
            ],
            "downloading_links": [
                "https://www.mediafire.com/file/9u3pedv5e2tv5w9/%5BWitanime.com%5D+RWTGI+EP+04+SD.zip/file",
                "https://workupload.com/file/qet89WPSLpT",
                "https://www.mp4upload.com/phf3qhs5mjb6",
                "https://gofile.io/d/mwNKDl",
                "https://www.mediafire.com/file/4lhgcpbpm22lkcs/%5BWitanime.com%5D+RWTGI+EP+04+HD.zip/file",
                "https://workupload.com/file/NUTR3sqcgpZ",
                "https://www.mp4upload.com/um94gbtuxp3v",
                "https://gofile.io/d/6cIDHG",
                "https://www.mediafire.com/file/fszgnok7bzqp698/%5BWitanime.com%5D+RWTGI+EP+04+FHD.zip/file"
            ]
        },
        "5": {
            "streaming_links": [
                "https://yonaplay.net/embed.php?id=16569",
                "https://ok.ru/videoembed/8036089400006",
                "https://videa.hu/player?v=vzM3zri7ncycBeiv",
                "https://www.dailymotion.com/embed/video/x98l72q",
                "https://ok.ru/videoembed/8036118956742",
                "https://ok.ru/videoembed/8036164242118",
                "https://videa.hu/player?v=sCaZ3OxDJZSms9mV",
                "https://www.dailymotion.com/embed/video/x98l72q"
            ],
            "downloading_links": [
                "https://www.mediafire.com/file/gmejr6yj3ydhju4/%5BWitanime.com%5D+RWTGI+EP+05+SD.zip/file",
                "https://workupload.com/file/cPyQzzTsgYE",
                "https://www.mp4upload.com/n2ypfb9d1w5z",
                "https://gofile.io/d/d8fSZA",
                "https://www.mediafire.com/file/uhuafppd7aplaty/%5BWitanime.com%5D+RWTGI+EP+05+HD.zip/file",
                "https://workupload.com/file/tRVxGj4S62F",
                "https://www.mp4upload.com/ijk9jzo75jtb",
                "https://gofile.io/d/JqoA9A",
                "https://www.mediafire.com/file/gl83e9893sryfjd/[Witanime.com]+RWTGI+EP+05+FHD.zip/file"
            ]
        },
        "6": {
            "streaming_links": [
                "https://yonaplay.net/embed.php?id=16631",
                "https://ok.ru/videoembed/8212902644422",
                "https://videa.hu/player?v=OKIpZ8Xqoe1GcIHJ",
                "https://www.dailymotion.com/embed/video/x98z6vm",
                "https://ok.ru/videoembed/8212978600646",
                "https://ok.ru/videoembed/8213001210566",
                "https://videa.hu/player?v=SzkxRpSLvoQto4Tk",
                "https://www.dailymotion.com/embed/video/x98z6vm"
            ],
            "downloading_links": [
                "https://www.mediafire.com/file/njhwezbilk14qwt/%5BWitanime.com%5D+RWTGI+EP+06+SD.zip/file",
                "https://workupload.com/file/ZVjHJ8HcALv",
                "https://www.mp4upload.com/6p2mqzpm4o0i",
                "https://gofile.io/d/NlacVt",
                "https://www.mediafire.com/file/4v664cuoo0cupjh/%5BWitanime.com%5D+RWTGI+EP+06+HD.zip/file",
                "https://workupload.com/file/SXEFM9928mn",
                "https://www.mp4upload.com/x4ls6m499q1k",
                "https://gofile.io/d/NlacVt",
                "https://www.mediafire.com/file/uqk83hdz1wwf6ge/[Witanime.com]+RWTGI+EP+06+FHD.zip/file"
            ]
        },
        "7": {
            "streaming_links": [
                "https://yonaplay.net/embed.php?id=16692",
                "https://ok.ru/videoembed/8363016456902",
                "https://videa.hu/player?v=SUO8JElCFwgGqpg7",
                "https://www.dailymotion.com/embed/video/x99d70w",
                "https://ok.ru/videoembed/8363048241862",
                "https://ok.ru/videoembed/8363077601990",
                "https://videa.hu/player?v=9Yo953fbDPXmHkYK",
                "https://www.dailymotion.com/embed/video/x99d70w"
            ],
            "downloading_links": [
                "https://www.mediafire.com/file/6gxuyet5vghhy04/%5BWitanime.com%5D+RWTGI+EP+07+SD.zip/file",
                "https://workupload.com/file/yuZMZ7vFh9u",
                "https://www.mp4upload.com/06ddlfxwg8l2",
                "https://gofile.io/d/i5xC3Q",
                "https://www.mediafire.com/file/yed4f8222wbg1oo/%5BWitanime.com%5D+RWTGI+EP+07+HD.zip/file",
                "https://workupload.com/file/SGur3zfTZJN",
                "https://www.mp4upload.com/azr6tm7u2onl",
                "https://gofile.io/d/GZ7mOC",
                "https://www.mediafire.com/file/exi27sx7zo1t33r/[Witanime.com]+RWTGI+EP+07+FHD.zip/file"
            ]
        },
        "8": {
            "streaming_links": [
                "https://yonaplay.net/embed.php?id=16758",
                "https://ok.ru/videoembed/8531491293894",
                "https://videa.hu/player?v=G1eCSPbWS1BSWrnz",
                "https://www.dailymotion.com/embed/video/x99r2g4",
                "https://ok.ru/videoembed/8531525962438",
                "https://ok.ru/videoembed/8531572951750",
                "https://videa.hu/player?v=p9Z8mN6mAbGtplGg",
                "https://www.dailymotion.com/embed/video/x99r2g4"
            ],
            "downloading_links": [
                "https://www.mediafire.com/file/1p9lnv8xengqh82/%5BWitanime.com%5D+RWTGI+EP+08+SD.zip/file",
                "https://workupload.com/file/YJLpQbhNZuN",
                "https://www.mp4upload.com/i80yrseqkhn1",
                "https://gofile.io/d/1bgtcJ",
                "https://www.mediafire.com/file/qvgnqvw7kntpij8/%5BWitanime.com%5D+RWTGI+EP+08+HD.zip/file",
                "https://workupload.com/file/YEvw93B2tRL",
                "https://www.mp4upload.com/srsz9vyw7lem",
                "https://gofile.io/d/1bgtcJ",
                "https://www.mediafire.com/file/ayjc6vs4ezms4kd/[Witanime.com]+RWTGI+EP+08+FHD.zip/file"
            ]
        },
        "9": {
            "streaming_links": [
                "https://yonaplay.net/embed.php?id=16812",
                "https://ok.ru/videoembed/8711096634054",
                "https://videa.hu/player?v=Fdj0zrCTlkLxrAHd",
                "https://www.dailymotion.com/embed/video/x9a4iyy",
                "https://ok.ru/videoembed/8711139625670",
                "https://ok.ru/videoembed/8711182617286",
                "https://videa.hu/player?v=BJYTrl2zTlmTnwyU",
                "https://www.dailymotion.com/embed/video/x9a4iyy"
            ],
            "downloading_links": [
                "https://www.mediafire.com/file/qsw0ssg1lzlkkxo/%5BWitanime.com%5D+RWTGI+EP+09+SD.zip/file",
                "https://workupload.com/file/6sQ8YWYJ6TD",
                "https://www.mp4upload.com/n4b4u123eky9",
                "https://gofile.io/d/n5QgwA",
                "https://www.mediafire.com/file/dttjnv3frwavpwk/%5BWitanime.com%5D+RWTGI+EP+09+HD.zip/file",
                "https://workupload.com/file/G2rq7yMfnwQ",
                "https://www.mp4upload.com/uoy3rsy9bkbq",
                "https://gofile.io/d/VJLFfy",
                "https://www.mediafire.com/file/nnr7gp8lvdwxqvk/[Witanime.com]+RWTGI+EP+09+FHD.zip/file"
            ]
        },
        "10": {
            "streaming_links": [
                "https://yonaplay.net/embed.php?id=16878",
                "https://ok.ru/videoembed/8889483332294",
                "https://videa.hu/player?v=wXQrCaYEcU8bJwFx",
                "https://www.dailymotion.com/embed/video/x9ai0li",
                "https://ok.ru/videoembed/8889523571398",
                "https://ok.ru/videoembed/8889555225286",
                "https://videa.hu/player?v=9XxubWKcotIga7dZ",
                "https://www.dailymotion.com/embed/video/x9ai0li"
            ],
            "downloading_links": [
                "https://www.mediafire.com/file/11hmb5q4vdck345/%5BWitanime.com%5D+RWTGI+EP+10+SD.zip/file",
                "https://workupload.com/file/grSxjhyxteT",
                "https://www.mp4upload.com/vwof9bvb2bkq",
                "https://gofile.io/d/TinURs",
                "https://www.mediafire.com/file/oqdbm3rtbp13fmr/%5BWitanime.com%5D+RWTGI+EP+10+HD.zip/file",
                "https://workupload.com/file/rgWH58szhNr",
                "https://www.mp4upload.com/ozgnlfhao4id",
                "https://gofile.io/d/TinURs",
                "https://www.mediafire.com/file/swqqrmf0c0k7wpa/[Witanime.com]+RWTGI+EP+10+FHD.zip/file"
            ]
        },
        "11": {
            "streaming_links": [
                "https://yonaplay.net/embed.php?id=16932",
                "https://ok.ru/videoembed/8975003683526",
                "https://videa.hu/player?v=oInTu0NhvlTkyM71",
                "https://www.dailymotion.com/embed/video/x9avxc4",
                "https://ok.ru/videoembed/8975010826950",
                "https://ok.ru/videoembed/8975014300358",
                "https://videa.hu/player?v=2aOpYO7m6JIPyfUP",
                "https://www.dailymotion.com/embed/video/x9avxc4"
            ],
            "downloading_links": [
                "https://www.mediafire.com/file/jgh4zmjpgo4ds2x/%5BWitanime.com%5D+RWTGI+EP+11+SD.zip/file",
                "https://workupload.com/file/vpMVYaHVdQD",
                "https://www.mp4upload.com/lwbjm4g9yq63",
                "https://gofile.io/d/XOXMwZ",
                "https://www.mediafire.com/file/c468lwxypl6g08v/%5BWitanime.com%5D+RWTGI+EP+11+HD.zip/file",
                "https://workupload.com/file/c7R2pKqeZSw",
                "https://www.mp4upload.com/wi3l1o2gsuh2",
                "https://gofile.io/d/XOXMwZ",
                "https://www.mediafire.com/file/wew3o52ytlh0o0j/[Witanime.com]+RWTGI+EP+11+FHD.zip/file"
            ]
        },
        "12": {
            "streaming_links": [
                "https://yonaplay.net/embed.php?id=17042",
                "https://ok.ru/videoembed/9001602452166",
                "https://videa.hu/player?v=9voqyXUXd6oj9oy2",
                "https://www.dailymotion.com/embed/video/x9b97zm",
                "https://ok.ru/videoembed/9001611561670",
                "https://ok.ru/videoembed/9001618836166",
                "https://videa.hu/player?v=qn1OHEr0K8CHGmwJ",
                "https://www.dailymotion.com/embed/video/x9b97zm"
            ],
            "downloading_links": [
                "https://www.mediafire.com/file/wn3c91efm4vxufz/%5BWitanime.com%5D+RWTGI+EP+12+END+SD.zip/file",
                "https://workupload.com/file/6d5bhdPBHsD",
                "https://www.mp4upload.com/acpfu6kktogb",
                "https://gofile.io/d/2dGW0M",
                "https://www.mediafire.com/file/mg3qhib0ts3sfc7/%5BWitanime.com%5D+RWTGI+EP+12+END+HD.zip/file",
                "https://workupload.com/file/nsvnXfaHxPn",
                "https://www.mp4upload.com/e2r642y8jwr1",
                "https://gofile.io/d/kXF6r2",
                "https://www.mediafire.com/file/u02ii7ao1ltt1u9/[Witanime.com]+RWTGI+EP+12+END+FHD.zip/file"
            ]
        }
    }
}